[
  {
    "time_sec": 0,
    "description": "A woman is holding a bowl of food."
  },
  {
    "time_sec": 1,
    "description": "A woman is eating a sandwich."
  },
  {
    "time_sec": 2,
    "description": "A woman is eating food from a bowl."
  },
  {
    "time_sec": 3,
    "description": "A woman is holding a plate with food on it."
  },
  {
    "time_sec": 4,
    "description": "A woman is holding a plate with a sandwich on it."
  },
  {
    "time_sec": 5,
    "description": "A woman is holding a plate with a piece of food on it."
  },
  {
    "time_sec": 6,
    "description": "A woman is holding a plate with a piece of food on it."
  },
  {
    "time_sec": 7,
    "description": "A woman holding a plate with a sandwich on it."
  },
  {
    "time_sec": 8,
    "description": "A woman is holding a plate with a cookie on it."
  },
  {
    "time_sec": 9,
    "description": "A woman is holding a plate with a cookie on it."
  },
  {
    "time_sec": 10,
    "description": "A woman is holding a plate with a piece of food on it."
  },
  {
    "time_sec": 11,
    "description": "A woman is eating a pastry."
  },
  {
    "time_sec": 12,
    "description": "A woman is eating a donut."
  },
  {
    "time_sec": 13,
    "description": "A woman is eating a sandwich while standing in a bathroom."
  },
  {
    "time_sec": 14,
    "description": "A woman is holding a bowl of food."
  },
  {
    "time_sec": 15,
    "description": "A woman is holding a plate with food on it."
  },
  {
    "time_sec": 16,
    "description": "A woman is holding a plate with food on it."
  },
  {
    "time_sec": 17,
    "description": "A woman is holding a plate with food on it."
  },
  {
    "time_sec": 18,
    "description": "A woman is holding a plate with food on it."
  },
  {
    "time_sec": 19,
    "description": "A woman is holding a plate with a sandwich on it."
  }
]