[
  {
    "time_sec": 0,
    "description": "A man is standing in a kitchen."
  },
  {
    "time_sec": 1,
    "description": "A man is opening a refrigerator door."
  },
  {
    "time_sec": 2,
    "description": "A man is putting something in the refrigerator."
  },
  {
    "time_sec": 3,
    "description": "A man is standing in a kitchen, wearing plaid pants and a gray sweater."
  },
  {
    "time_sec": 4,
    "description": "A man is standing in a kitchen, wearing plaid pants and a gray sweater."
  },
  {
    "time_sec": 5,
    "description": "A man is standing in front of a stove."
  },
  {
    "time_sec": 6,
    "description": "A man is standing in a kitchen, wearing plaid pants and a gray sweater, and he is opening the"
  },
  {
    "time_sec": 7,
    "description": "A man is standing in a kitchen, cooking."
  },
  {
    "time_sec": 8,
    "description": "A man is standing in a kitchen, preparing food."
  },
  {
    "time_sec": 9,
    "description": "A man is standing in a kitchen, preparing food."
  },
  {
    "time_sec": 10,
    "description": "A man is standing in a kitchen, wearing plaid pants and a grey sweater."
  },
  {
    "time_sec": 11,
    "description": "A man is putting something in the oven."
  },
  {
    "time_sec": 12,
    "description": "A man is opening the refrigerator door."
  },
  {
    "time_sec": 13,
    "description": "A man is opening a refrigerator."
  },
  {
    "time_sec": 14,
    "description": "A man is opening a refrigerator."
  },
  {
    "time_sec": 15,
    "description": "A man is opening a refrigerator."
  },
  {
    "time_sec": 16,
    "description": "A man is opening the refrigerator door."
  },
  {
    "time_sec": 17,
    "description": "A man is walking in a kitchen."
  },
  {
    "time_sec": 18,
    "description": "A man is standing in front of a stove."
  },
  {
    "time_sec": 19,
    "description": "A man in a sweater is holding a cup of coffee."
  },
  {
    "time_sec": 20,
    "description": "A man drinking from a cup."
  },
  {
    "time_sec": 21,
    "description": "A man drinking from a cup."
  },
  {
    "time_sec": 22,
    "description": "A man drinking from a cup."
  },
  {
    "time_sec": 23,
    "description": "A man is standing in front of a stove."
  },
  {
    "time_sec": 24,
    "description": "A man is standing in a kitchen, wearing plaid pants and a sweater."
  }
]