[
  {
    "time_sec": 0,
    "description": "A woman is washing her hands in a bathroom."
  },
  {
    "time_sec": 1,
    "description": "A woman is washing her hands in a bathroom."
  },
  {
    "time_sec": 2,
    "description": "A woman is brushing her teeth."
  },
  {
    "time_sec": 3,
    "description": "A woman is brushing her teeth."
  },
  {
    "time_sec": 4,
    "description": "A woman is covering her mouth with her hand."
  },
  {
    "time_sec": 5,
    "description": "A woman is putting on her makeup in the bathroom."
  },
  {
    "time_sec": 6,
    "description": "A woman is covering her mouth with her hand."
  },
  {
    "time_sec": 7,
    "description": "A woman is brushing her teeth."
  },
  {
    "time_sec": 8,
    "description": "A woman is talking on the phone."
  },
  {
    "time_sec": 9,
    "description": "A woman is making a funny face."
  },
  {
    "time_sec": 10,
    "description": "A woman is standing in front of a bathroom mirror."
  },
  {
    "time_sec": 11,
    "description": "A woman is holding her nose and laughing."
  },
  {
    "time_sec": 12,
    "description": "A woman is holding her hands to her face."
  },
  {
    "time_sec": 13,
    "description": "A woman is making a funny face."
  },
  {
    "time_sec": 14,
    "description": "A woman is talking on the phone."
  },
  {
    "time_sec": 15,
    "description": "A woman is opening her mouth wide."
  },
  {
    "time_sec": 16,
    "description": "A woman is making a funny face."
  },
  {
    "time_sec": 17,
    "description": "A woman is making a funny face."
  },
  {
    "time_sec": 18,
    "description": "A woman is laughing in a bathroom."
  },
  {
    "time_sec": 19,
    "description": "A woman is laughing in a bathroom."
  },
  {
    "time_sec": 20,
    "description": "A woman is laughing in a bathroom."
  },
  {
    "time_sec": 21,
    "description": "A woman is standing in a room and covering her mouth."
  },
  {
    "time_sec": 22,
    "description": "A woman is standing in a bathroom and putting her hand on her face."
  },
  {
    "time_sec": 23,
    "description": "A woman is standing in a bathroom and putting her hand on her face."
  },
  {
    "time_sec": 24,
    "description": "A woman is making a funny face."
  },
  {
    "time_sec": 25,
    "description": "A woman is talking on a cell phone."
  },
  {
    "time_sec": 26,
    "description": "A woman is talking on her cell phone."
  },
  {
    "time_sec": 27,
    "description": "A woman is talking on her cell phone."
  },
  {
    "time_sec": 28,
    "description": "A woman is talking on her cell phone."
  },
  {
    "time_sec": 29,
    "description": "A woman is talking on her cell phone."
  }
]