[
  {
    "time_sec": 0,
    "description": "A man is holding a red blanket."
  },
  {
    "time_sec": 1,
    "description": "A man is holding a red blanket."
  },
  {
    "time_sec": 2,
    "description": "A man is holding a red fabric while another man is holding a blue fabric."
  },
  {
    "time_sec": 3,
    "description": "A man is holding a red blanket."
  },
  {
    "time_sec": 4,
    "description": "A man is holding a red blanket."
  },
  {
    "time_sec": 5,
    "description": "A man is holding a woman in his arms."
  },
  {
    "time_sec": 6,
    "description": "A man is holding a red cloth while walking down a staircase."
  },
  {
    "time_sec": 7,
    "description": "A man is holding a red fabric while standing on a staircase."
  },
  {
    "time_sec": 8,
    "description": "A man is walking down a staircase."
  },
  {
    "time_sec": 9,
    "description": "A man is helping another person down a set of stairs."
  },
  {
    "time_sec": 10,
    "description": "A person is holding a blanket while standing on a staircase."
  },
  {
    "time_sec": 11,
    "description": "A man is holding a black coat on a staircase."
  },
  {
    "time_sec": 12,
    "description": "A man is holding a jacket while another man is holding a coat."
  },
  {
    "time_sec": 13,
    "description": "A man is holding a blue cloth while another person is holding a yellow cloth."
  },
  {
    "time_sec": 14,
    "description": "A person is holding a blue cloth."
  },
  {
    "time_sec": 15,
    "description": "A man is pulling a blue cloth from his pants."
  },
  {
    "time_sec": 16,
    "description": "A man is holding a blue cloth while walking down a staircase."
  },
  {
    "time_sec": 17,
    "description": "A man is holding a jacket over his arm."
  },
  {
    "time_sec": 18,
    "description": "A man is holding a bag while standing on a staircase."
  },
  {
    "time_sec": 19,
    "description": "A man is walking down a staircase."
  },
  {
    "time_sec": 20,
    "description": "A man is bending over to pick up a dog."
  },
  {
    "time_sec": 21,
    "description": "A man is sitting on the stairs and putting something in his backpack."
  },
  {
    "time_sec": 22,
    "description": "A man is sitting on the stairs and looking at his luggage."
  },
  {
    "time_sec": 23,
    "description": "A man is sitting on the stairs."
  },
  {
    "time_sec": 24,
    "description": "A man is sitting on the stairs and putting on his shoes."
  },
  {
    "time_sec": 25,
    "description": "A man is sitting on the stairs with a tennis ball in his hand."
  },
  {
    "time_sec": 26,
    "description": "A man is sitting on the stairs and playing with a frisbee."
  },
  {
    "time_sec": 27,
    "description": "A man is sitting on the stairs while holding a frisbee."
  },
  {
    "time_sec": 28,
    "description": "A man is sitting on the stairs and brushing his teeth."
  }
]