[
  {
    "time_sec": 0,
    "description": "A boy is standing on a staircase."
  },
  {
    "time_sec": 1,
    "description": "A man is standing on a staircase."
  },
  {
    "time_sec": 2,
    "description": "A man is standing on a staircase."
  },
  {
    "time_sec": 3,
    "description": "A man is standing on a staircase."
  },
  {
    "time_sec": 4,
    "description": "A man is standing on a staircase while talking on his cell phone."
  },
  {
    "time_sec": 5,
    "description": "A man is standing on a staircase."
  },
  {
    "time_sec": 6,
    "description": "A man is standing on a staircase."
  },
  {
    "time_sec": 7,
    "description": "A woman is standing on a staircase."
  },
  {
    "time_sec": 8,
    "description": "A person is standing on a staircase."
  },
  {
    "time_sec": 9,
    "description": "A boy is walking up a flight of stairs while carrying a bag."
  },
  {
    "time_sec": 10,
    "description": "A person is standing on a staircase."
  },
  {
    "time_sec": 11,
    "description": "A boy is standing on a staircase holding a jacket."
  },
  {
    "time_sec": 12,
    "description": "A woman is standing on a staircase holding a towel."
  },
  {
    "time_sec": 13,
    "description": "A boy is holding a shirt and walking down a staircase."
  },
  {
    "time_sec": 14,
    "description": "A boy is holding a jacket while standing on a staircase."
  },
  {
    "time_sec": 15,
    "description": "A woman is holding a jacket and standing on a staircase."
  },
  {
    "time_sec": 16,
    "description": "A boy is holding a jacket while walking down a staircase."
  },
  {
    "time_sec": 17,
    "description": "A man is putting clothes on a rack."
  },
  {
    "time_sec": 18,
    "description": "A boy is walking down a staircase."
  },
  {
    "time_sec": 19,
    "description": "A boy is climbing the stairs."
  },
  {
    "time_sec": 20,
    "description": "A boy is eating a lollipop."
  },
  {
    "time_sec": 21,
    "description": "A boy drinking from a cup."
  },
  {
    "time_sec": 22,
    "description": "A boy drinking from a bottle."
  },
  {
    "time_sec": 23,
    "description": "A boy is blowing bubbles on the stairs."
  },
  {
    "time_sec": 24,
    "description": "A boy is wiping a towel on a wall."
  },
  {
    "time_sec": 25,
    "description": "A boy is wiping a towel on a wall."
  },
  {
    "time_sec": 26,
    "description": "A boy is holding a towel."
  },
  {
    "time_sec": 27,
    "description": "A boy is holding a towel."
  },
  {
    "time_sec": 28,
    "description": "A boy is holding a towel and looking down."
  },
  {
    "time_sec": 29,
    "description": "A boy is holding a towel."
  },
  {
    "time_sec": 30,
    "description": "A boy is holding a towel."
  },
  {
    "time_sec": 31,
    "description": "A boy is holding a towel."
  },
  {
    "time_sec": 32,
    "description": "A boy is holding a towel."
  }
]